scandi_reddit/__init__.py
scandi_reddit/build.py
scandi_reddit/cli.py
scandi_reddit/download.py
scandi_reddit/language_filter.py
scandi_reddit/postprocess.py
scandi_reddit-0.2.1.dist-info/entry_points.txt
scandi_reddit-0.2.1.dist-info/LICENSE
scandi_reddit-0.2.1.dist-info/WHEEL
scandi_reddit-0.2.1.dist-info/METADATA
scandi_reddit-0.2.1.dist-info/RECORD
