Metadata-Version: 2.1
Name: scandi-reddit
Version: 0.2.1
Summary: Construction of a Scandinavian Reddit dataset.
License: MIT
Author: Dan Saattrup Nielsen
Author-email: dan.nielsen@alexandra.dk
Requires-Python: >=3.8,<3.11
Classifier: License :: OSI Approved :: MIT License
Classifier: Programming Language :: Python :: 3
Classifier: Programming Language :: Python :: 3.8
Classifier: Programming Language :: Python :: 3.9
Classifier: Programming Language :: Python :: 3.10
Requires-Dist: datasets (>=2.7.1,<3.0.0)
Requires-Dist: datasketch (>=1.5.8,<2.0.0)
Requires-Dist: luga (>=0.2.6,<0.3.0)
Requires-Dist: more-itertools (>=9.0.0,<10.0.0)
Requires-Dist: nlp-dedup (>=0.1.1,<0.2.0)
Requires-Dist: pandas (>=1.5.2,<2.0.0)
Requires-Dist: wget (>=3.2,<4.0)
Requires-Dist: zstandard (>=0.19.0,<0.20.0)
